[
[
  { "id": "Container 1", "label": "" },
  { "id": "Container 2", "label": "" },
  { "id": "Container 3", "label": "" },
  { "id": "Container 4", "label": "" },
  { "id": "Container 5", "label": "" },
  { "id": "Container 6", "label": "" },
  { "id": "Container 7", "label": "" },
  { "id": "Container 8", "label": "" },
  { "id": "Container 9", "label": "" },
  { "id": "Container 10", "label": "" },
  { "id": "Container 11", "label": "" },
  { "id": "Container 12", "label": "" },
  { "id": "Container 13", "label": "" },
  { "id": "Container 14", "label": "" },
  { "id": "Container 15", "label": "" },
  { "id": "Container 16", "label": "" },
  { "id": "Container 17", "label": "" },
  { "id": "Container 18", "label": "" },
  { "id": "Container 19", "label": "" },
  { "id": "Container 20", "label": "" },
  { "id": "Container 21", "label": "" },
  { "id": "Container 22", "label": "" },
  { "id": "Container 23", "label": "" },
  { "id": "Container 24", "label": "" },
  { "id": "Container 25", "label": "" },
  { "id": "Container 26", "label": "" },
  { "id": "Container 27", "label": "" },
  { "id": "Container 28", "label": "" },
  { "id": "Container 29", "label": "" },
  { "id": "Container 30", "label": "" },
  { "id": "Container 31", "label": "" },
  { "id": "Container 32", "label": "" },
  { "id": "Container 33", "label": "" },
  { "id": "Container 34", "label": "" },
  { "id": "Container 35", "label": "" },
  { "id": "Container 36", "label": "" },
  { "id": "Container 37", "label": "" },
  { "id": "Container 38", "label": "" },
  { "id": "Container 39", "label": "" },
  { "id": "Container 40", "label": "" },
  { "id": "Container 41", "label": "" },
  { "id": "Container 42", "label": "" },
  { "id": "Container 43", "label": "" },
  { "id": "Container 44", "label": "" },
  { "id": "Container 45", "label": "" },
  { "id": "Container 46", "label": "" },
  { "id": "Container 47", "label": "" },
  { "id": "Container 48", "label": "" },
  { "id": "Container 49", "label": "" },
  { "id": "Container 50", "label": "" }
]

]

